README.rst
setup.cfg
setup.py
hoverpy/__init__.py
hoverpy/cert.pem
hoverpy/config.py
hoverpy/decorators.py
hoverpy/hp.py
hoverpy/testing.py
hoverpy.egg-info/PKG-INFO
hoverpy.egg-info/SOURCES.txt
hoverpy.egg-info/dependency_links.txt
hoverpy.egg-info/requires.txt
hoverpy.egg-info/top_level.txt
hoverpy/lib/__init__.py
hoverpy/lib/tor.py