Metadata-Version: 1.1
Name: hoverpy
Version: 0.2.2
Summary: A python library for HoverFly
Home-page: https://github.com/SpectoLabs/hoverpy
Author: SpectoLabs
Author-email: shyal@shyal.com
License: UNKNOWN
Download-URL: https://github.com/SpectoLabs/hoverpy/tarball/0.2.2
Keywords: testing,rest,caching,ci
Platform: UNKNOWN
